op_research/__init__.py
op_research/oreaserch.py
op_research-0.0.2.dist-info/WHEEL
op_research-0.0.2.dist-info/METADATA
op_research-0.0.2.dist-info/RECORD
