Metadata-Version: 2.1
Name: op-research
Version: 0.0.2
Summary: package for solving operational research problems
Home-page: https://github.com/Rehan-stack/op-research
License: MIT
Keywords: op-research,operational-research,simplex-method,two-phase method,math
Author: rehan ahmed
Author-email: rehanahmedahmed007@gmail.com
Requires-Python: >=3.10,<4.0
Classifier: License :: OSI Approved :: MIT License
Classifier: Operating System :: OS Independent
Classifier: Programming Language :: Python :: 3
Classifier: Programming Language :: Python :: 3.10
Classifier: Programming Language :: Python :: 3.6
Classifier: Programming Language :: Python :: 3.7
Classifier: Programming Language :: Python :: 3.8
Classifier: Programming Language :: Python :: 3.9
Project-URL: Repository, https://github.com/Rehan-stack/op-research
